LICENSE
README.rst
setup.cfg
setup.py
cardinal_pythonlib/__init__.py
cardinal_pythonlib/argparse_func.py
cardinal_pythonlib/athena_ohdsi.py
cardinal_pythonlib/betweendict.py
cardinal_pythonlib/buildfunc.py
cardinal_pythonlib/chebi.py
cardinal_pythonlib/classes.py
cardinal_pythonlib/cmdline.py
cardinal_pythonlib/colander_utils.py
cardinal_pythonlib/compression.py
cardinal_pythonlib/configfiles.py
cardinal_pythonlib/contexts.py
cardinal_pythonlib/convert.py
cardinal_pythonlib/crypto.py
cardinal_pythonlib/datamapping.py
cardinal_pythonlib/datetimefunc.py
cardinal_pythonlib/dbfunc.py
cardinal_pythonlib/debugging.py
cardinal_pythonlib/deform_utils.py
cardinal_pythonlib/dicts.py
cardinal_pythonlib/docker.py
cardinal_pythonlib/dogpile_cache.py
cardinal_pythonlib/dsp.py
cardinal_pythonlib/enumlike.py
cardinal_pythonlib/excel.py
cardinal_pythonlib/exceptions.py
cardinal_pythonlib/extract_text.py
cardinal_pythonlib/file_io.py
cardinal_pythonlib/fileops.py
cardinal_pythonlib/formatting.py
cardinal_pythonlib/getch.py
cardinal_pythonlib/hash.py
cardinal_pythonlib/httpconst.py
cardinal_pythonlib/interval.py
cardinal_pythonlib/iterhelp.py
cardinal_pythonlib/lang.py
cardinal_pythonlib/lists.py
cardinal_pythonlib/logs.py
cardinal_pythonlib/maths_numpy.py
cardinal_pythonlib/maths_py.py
cardinal_pythonlib/metaclasses.py
cardinal_pythonlib/module_version.py
cardinal_pythonlib/modules.py
cardinal_pythonlib/network.py
cardinal_pythonlib/nhs.py
cardinal_pythonlib/parallel.py
cardinal_pythonlib/pdf.py
cardinal_pythonlib/platformfunc.py
cardinal_pythonlib/plot.py
cardinal_pythonlib/probability.py
cardinal_pythonlib/process.py
cardinal_pythonlib/profiling.py
cardinal_pythonlib/progress.py
cardinal_pythonlib/randomness.py
cardinal_pythonlib/rate_limiting.py
cardinal_pythonlib/regexfunc.py
cardinal_pythonlib/register_db_with_odbc.py
cardinal_pythonlib/reprfunc.py
cardinal_pythonlib/rnc_text.py
cardinal_pythonlib/rnc_web.py
cardinal_pythonlib/rounding.py
cardinal_pythonlib/rpm.py
cardinal_pythonlib.egg-info/PKG-INFO
cardinal_pythonlib.egg-info/SOURCES.txt
cardinal_pythonlib.egg-info/dependency_links.txt
cardinal_pythonlib.egg-info/entry_points.txt
cardinal_pythonlib.egg-info/requires.txt
cardinal_pythonlib.egg-info/top_level.txt
