Metadata-Version: 2.1
Name: cardinal-pythonlib
Version: 2.1.1
Summary: Miscellaneous Python libraries
Home-page: https://github.com/RudolfCardinal/pythonlib
Author: Rudolf Cardinal
Author-email: rudolf@pobox.com
License: Apache License 2.0
Keywords: cardinal
Classifier: Development Status :: 4 - Beta
Classifier: Intended Audience :: Developers
Classifier: License :: OSI Approved :: Apache Software License
Classifier: Natural Language :: English
Classifier: Operating System :: OS Independent
Classifier: Programming Language :: Python :: 3
Classifier: Programming Language :: Python :: 3.8
Classifier: Programming Language :: Python :: 3.9
Classifier: Programming Language :: Python :: 3.10
Classifier: Topic :: Software Development :: Libraries
License-File: LICENSE
